{"by":"rconti","id":22891129,"kids":[22891156],"parent":22891095,"text":"Can you elaborate like I&#x27;m 5? Just very high level for those of us who only know &quot;they charge a flat fee and a percent which makes microtransactions hard&quot;.<p>What are the strategies&#x2F;thoughts in the industry? Holding and batching payments on a per-user basis? Trying to get agreements so you can batch payments on a per-processor or per-network agreement? Hourly? Daily? Weekly?","time":1587055142,"type":"comment"}