{"by":"antonkm","id":22892219,"kids":[22892492,22892282,22892358,22892438,22892303],"parent":22892141,"text":"Swede here. Really baffling for me too. My kids have pretty much never even seen cash. I use the nationwide app Swish to send money to people using their phone number (almost every Swede is connected since it&#x27;s pushed by all big banks) and only use contactless credit card.<p>How come Germany is so cash positive? Personally I think Sweden has gone a bit far, where some old people have been put in a weird spot where they can&#x27;t pay because they&#x27;re technologically illiterate.","time":1587062657,"type":"comment"}